matchescu/clustering/__init__.py
matchescu/clustering/_base.py
matchescu/clustering/_cc.py
matchescu/clustering/_center.py
matchescu/clustering/_corr.py
matchescu/clustering/_ecp.py
matchescu/clustering/_gacl.py
matchescu/clustering/_hac.py
matchescu/clustering/_mcl.py
matchescu/clustering/_wcc.py
matchescu/py.typed
matchescu_clustering-0.10.0.dist-info/LICENSE
matchescu_clustering-0.10.0.dist-info/METADATA
matchescu_clustering-0.10.0.dist-info/WHEEL
matchescu_clustering-0.10.0.dist-info/RECORD
