Metadata-Version: 2.1
Name: matchescu-clustering
Version: 0.10.0
Summary: Clustering routines and data structures for entity resolution
Author: Andrei Olar
Author-email: andrei.olar@ubbcluj.ro
Requires-Python: >=3.12,<4.0
Classifier: Programming Language :: Python :: 3
Classifier: Programming Language :: Python :: 3.12
Classifier: Programming Language :: Python :: 3.13
Requires-Dist: markov-clustering (==0.0.6.*)
Requires-Dist: matchescu-base (>=0.22.1,<0.23.0)
Requires-Dist: numpy (>=2.2.4,<3.0.0)
Requires-Dist: scikit-learn (>=1.6.1,<2.0.0)
